[
	{
  "event": "func_pre",
  "target": {
    "@": 166239592,
    "class": "com.example.set.Customer",
    "id": 0,
    "name": null
  },
  "args": [
    0,
    {
      "@": 791885625,
      "class": "java.lang.String",
      "const": "Mario"
    }
  ],
  "name": "com.example.set.Customer.init"
},
	{
  "event": "func_post",
  "target": {
    "@": 166239592,
    "class": "com.example.set.Customer",
    "id": 0,
    "name": {
      "@": 791885625,
      "class": "java.lang.String",
      "const": "Mario"
    }
  },
  "args": [
    0,
    {
      "@": 791885625,
      "class": "java.lang.String",
      "const": "Mario"
    }
  ],
  "name": "com.example.set.Customer.init"
},
	{
  "event": "func_pre",
  "target": {
    "@": 166239592,
    "class": "com.example.set.Customer",
    "id": 0,
    "name": {
      "@": 791885625,
      "class": "java.lang.String",
      "const": "Mario"
    }
  },
  "args": [],
  "name": "com.example.set.Customer.getId"
},
	{
  "event": "func_post",
  "target": {
    "@": 166239592,
    "class": "com.example.set.Customer",
    "id": 0,
    "name": {
      "@": 791885625,
      "class": "java.lang.String",
      "const": "Mario"
    }
  },
  "args": [],
  "result": 0,
  "name": "com.example.set.Customer.getId"
},
	{
  "event": "func_pre",
  "target": {
    "@": 166239592,
    "class": "com.example.set.Customer",
    "id": 0,
    "name": {
      "@": 791885625,
      "class": "java.lang.String",
      "const": "Mario"
    }
  },
  "args": [],
  "name": "com.example.set.Customer.getName"
},
	{
  "event": "func_post",
  "target": {
    "@": 166239592,
    "class": "com.example.set.Customer",
    "id": 0,
    "name": {
      "@": 791885625,
      "class": "java.lang.String",
      "const": "Mario"
    }
  },
  "args": [],
  "result": {
    "@": 791885625,
    "class": "java.lang.String",
    "const": "Mario"
  },
  "name": "com.example.set.Customer.getName"
},
	{
  "event": "func_pre",
  "target": {
    "@": 2065530879,
    "class": "com.example.set.Customer",
    "id": 0,
    "name": null
  },
  "args": [
    1,
    {
      "@": 943010986,
      "class": "java.lang.String",
      "const": "Marco"
    }
  ],
  "name": "com.example.set.Customer.init"
},
	{
  "event": "func_post",
  "target": {
    "@": 2065530879,
    "class": "com.example.set.Customer",
    "id": 1,
    "name": {
      "@": 943010986,
      "class": "java.lang.String",
      "const": "Marco"
    }
  },
  "args": [
    1,
    {
      "@": 943010986,
      "class": "java.lang.String",
      "const": "Marco"
    }
  ],
  "name": "com.example.set.Customer.init"
},
	{
  "event": "func_pre",
  "target": {
    "@": 2065530879,
    "class": "com.example.set.Customer",
    "id": 1,
    "name": {
      "@": 943010986,
      "class": "java.lang.String",
      "const": "Marco"
    }
  },
  "args": [],
  "name": "com.example.set.Customer.getId"
},
	{
  "event": "func_post",
  "target": {
    "@": 2065530879,
    "class": "com.example.set.Customer",
    "id": 1,
    "name": {
      "@": 943010986,
      "class": "java.lang.String",
      "const": "Marco"
    }
  },
  "args": [],
  "result": 1,
  "name": "com.example.set.Customer.getId"
},
	{
  "event": "func_pre",
  "target": {
    "@": 2065530879,
    "class": "com.example.set.Customer",
    "id": 1,
    "name": {
      "@": 943010986,
      "class": "java.lang.String",
      "const": "Marco"
    }
  },
  "args": [],
  "name": "com.example.set.Customer.getName"
},
	{
  "event": "func_post",
  "target": {
    "@": 2065530879,
    "class": "com.example.set.Customer",
    "id": 1,
    "name": {
      "@": 943010986,
      "class": "java.lang.String",
      "const": "Marco"
    }
  },
  "args": [],
  "result": {
    "@": 943010986,
    "class": "java.lang.String",
    "const": "Marco"
  },
  "name": "com.example.set.Customer.getName"
},
	{
  "event": "func_pre",
  "target": {
    "@": 274064559,
    "class": "com.example.set.Customer",
    "id": 0,
    "name": null
  },
  "args": [
    2,
    {
      "@": 242131142,
      "class": "java.lang.String",
      "const": "Matteo"
    }
  ],
  "name": "com.example.set.Customer.init"
},
	{
  "event": "func_post",
  "target": {
    "@": 274064559,
    "class": "com.example.set.Customer",
    "id": 2,
    "name": {
      "@": 242131142,
      "class": "java.lang.String",
      "const": "Matteo"
    }
  },
  "args": [
    2,
    {
      "@": 242131142,
      "class": "java.lang.String",
      "const": "Matteo"
    }
  ],
  "name": "com.example.set.Customer.init"
},
	{
  "event": "func_pre",
  "target": {
    "@": 274064559,
    "class": "com.example.set.Customer",
    "id": 2,
    "name": {
      "@": 242131142,
      "class": "java.lang.String",
      "const": "Matteo"
    }
  },
  "args": [],
  "name": "com.example.set.Customer.getId"
},
	{
  "event": "func_post",
  "target": {
    "@": 274064559,
    "class": "com.example.set.Customer",
    "id": 2,
    "name": {
      "@": 242131142,
      "class": "java.lang.String",
      "const": "Matteo"
    }
  },
  "args": [],
  "result": 2,
  "name": "com.example.set.Customer.getId"
},
	{
  "event": "func_pre",
  "target": {
    "@": 274064559,
    "class": "com.example.set.Customer",
    "id": 2,
    "name": {
      "@": 242131142,
      "class": "java.lang.String",
      "const": "Matteo"
    }
  },
  "args": [],
  "name": "com.example.set.Customer.getName"
},
	{
  "event": "func_post",
  "target": {
    "@": 274064559,
    "class": "com.example.set.Customer",
    "id": 2,
    "name": {
      "@": 242131142,
      "class": "java.lang.String",
      "const": "Matteo"
    }
  },
  "args": [],
  "result": {
    "@": 242131142,
    "class": "java.lang.String",
    "const": "Matteo"
  },
  "name": "com.example.set.Customer.getName"
},
	{
  "event": "func_pre",
  "target": "com.example.set.MySet",
  "args": [
    {
      "@": 879505317,
      "class": "java.lang.Integer",
      "const": 2
    },
    {
      "@": 879505317,
      "class": "java.lang.Integer",
      "const": 2
    }
  ],
  "name": "com.example.set.MySet.sum"
},
	{
  "event": "func_post",
  "target": "com.example.set.MySet",
  "args": [
    {
      "@": 879505317,
      "class": "java.lang.Integer",
      "const": 2
    },
    {
      "@": 879505317,
      "class": "java.lang.Integer",
      "const": 2
    }
  ],
  "result": 4,
  "name": "com.example.set.MySet.sum"
},
	{
  "event": "func_pre",
  "target": {
    "@": 1129670968,
    "class": "com.example.set.Counter",
    "val": 0,
    "z": null
  },
  "args": [],
  "name": "com.example.set.Counter.inc"
},
	{
  "event": "func_post",
  "target": {
    "@": 1129670968,
    "class": "com.example.set.Counter",
    "val": 1,
    "z": null
  },
  "args": [],
  "name": "com.example.set.Counter.inc"
},
	{
  "event": "func_pre",
  "target": {
    "@": 1129670968,
    "class": "com.example.set.Counter",
    "val": 1,
    "z": null
  },
  "args": [],
  "name": "com.example.set.Counter.inc"
},
	{
  "event": "func_post",
  "target": {
    "@": 1129670968,
    "class": "com.example.set.Counter",
    "val": 2,
    "z": null
  },
  "args": [],
  "name": "com.example.set.Counter.inc"
},
	{
  "event": "func_pre",
  "target": {
    "@": 1129670968,
    "class": "com.example.set.Counter",
    "val": 2,
    "z": null
  },
  "args": [],
  "name": "com.example.set.Counter.getVal"
},
	{
  "event": "func_post",
  "target": {
    "@": 1129670968,
    "class": "com.example.set.Counter",
    "val": 2,
    "z": null
  },
  "args": [],
  "result": 2,
  "name": "com.example.set.Counter.getVal"
},
	{
  "event": "func_pre",
  "target": {
    "@": 2008017533,
    "class": "com.example.set.Counter",
    "val": 0,
    "z": null
  },
  "args": [],
  "name": "com.example.set.Counter.getVal"
},
	{
  "event": "func_post",
  "target": {
    "@": 2008017533,
    "class": "com.example.set.Counter",
    "val": 0,
    "z": null
  },
  "args": [],
  "result": 0,
  "name": "com.example.set.Counter.getVal"
},
	{
  "event": "func_pre",
  "target": {
    "@": 1129670968,
    "class": "com.example.set.Counter",
    "val": 2,
    "z": null
  },
  "args": [
    {
      "@": 2008017533,
      "class": "com.example.set.Counter",
      "val": 0,
      "z": null
    }
  ],
  "name": "com.example.set.Counter.copy"
},
	{
  "event": "func_post",
  "target": {
    "@": 1129670968,
    "class": "com.example.set.Counter",
    "val": 0,
    "z": null
  },
  "args": [
    {
      "@": 2008017533,
      "class": "com.example.set.Counter",
      "val": 0,
      "z": null
    }
  ],
  "name": "com.example.set.Counter.copy"
},
	{
  "event": "func_pre",
  "target": {
    "@": 1129670968,
    "class": "com.example.set.Counter",
    "val": 0,
    "z": null
  },
  "args": [],
  "name": "com.example.set.Counter.getVal"
},
	{
  "event": "func_post",
  "target": {
    "@": 1129670968,
    "class": "com.example.set.Counter",
    "val": 0,
    "z": null
  },
  "args": [],
  "result": 0,
  "name": "com.example.set.Counter.getVal"
},
	{
  "event": "func_pre",
  "target": {
    "@": 1129670968,
    "class": "com.example.set.Counter",
    "val": 0,
    "z": null
  },
  "args": [],
  "name": "com.example.set.Counter.reset"
},
	{
  "event": "func_post",
  "target": {
    "@": 1129670968,
    "class": "com.example.set.Counter",
    "val": 0,
    "z": null
  },
  "args": [],
  "name": "com.example.set.Counter.reset"
},
	{
  "event": "func_pre",
  "target": {
    "@": 1129670968,
    "class": "com.example.set.Counter",
    "val": 0,
    "z": null
  },
  "args": [
    100
  ],
  "name": "com.example.set.Counter.setVal"
},
	{
  "event": "func_post",
  "target": {
    "@": 1129670968,
    "class": "com.example.set.Counter",
    "val": 100,
    "z": null
  },
  "args": [
    100
  ],
  "name": "com.example.set.Counter.setVal"
},
	{
  "event": "func_pre",
  "target": {
    "@": 1129670968,
    "class": "com.example.set.Counter",
    "val": 100,
    "z": null
  },
  "args": [],
  "name": "com.example.set.Counter.getVal"
},
	{
  "event": "func_post",
  "target": {
    "@": 1129670968,
    "class": "com.example.set.Counter",
    "val": 100,
    "z": null
  },
  "args": [],
  "result": 100,
  "name": "com.example.set.Counter.getVal"
}
]